{"DL": {"districts": {"North West": {"section": {"5": 1, "6": 1}}, "South East": {"section": {"6": 1, "12": 1}}}, "section": {"5": 1, "6": 2, "12": 1}}, "JH": {"districts": {"Daltonganj": {"section": {"4": 1}}, "Garhwa": {"section": {"8": 1, "11": 1}}, "Hazaribagh": {"section": {"3": 1, "4": 2}}, "Ranchi": {"section": {"4": 1, "8": 1}}}, "section": {"3": 1, "4": 4, "8": 2, "11": 1}}, "KA": {"districts": {"DAKSHINA KANNADA": {"section": {"12": 1}}}, "section": {"12": 1}}, "MH": {"districts": {"Amravati": {"section": {"8": 1, "12": 3}}, "Aurangabad": {"section": {"11": 1, "12": 1}}, "Beed": {"section": {"12": 2}}, "Buldhana": {"section": {"3": 1, "4": 1, "8": 1, "11": 1, "12": 1}}, "Chandrapur": {"section": {"4": 1, "8": 1}}, "Dhule": {"section": {"12": 3, "23": 2}}, "Jalgaon": {"section": {"12": 1}}, "Jalna": {"section": {"12": 1}}, "Nashik": {"section": {"12": 1}}, "Osmanabad": {"section": {"8": 1, "12": 1, "14": 1}}, "Pune": {"section": {"8": 1, "11": 2, "12": 7}}, "Raigad": {"section": {"11": 2, "12": 3, "14": 1}}, "Satara": {"section": {"12": 1}}, "Thane": {"section": {"4": 1, "11": 1, "12": 1, "17": 1, "18": 1, "unknown": 1}}, "Wardha": {"section": {"2": 1, "3": 1, "11": 1, "12": 1}}, "Washim": {"section": {"8": 1, "11": 1}}}, "section": {"2": 1, "3": 2, "4": 3, "8": 6, "11": 9, "12": 27, "14": 2, "17": 1, "18": 1, "23": 2, "unknown": 1}}, "RJ": {"districts": {"Ajmer": {"section": {"4": 1, "8": 1, "12": 1}}, "Banswara": {"section": {"12": 1, "14": 1}}, "Dungarpur": {"section": {"3": 1, "4": 1, "11": 1}}, "Jaipur Metro": {"section": {"12": 1}}, "Jodhpur Metro": {"section": {"7": 1, "8": 1, "18": 1}}, "Kota": {"section": {"7": 1, "8": 1, "11": 1, "12": 1, "13": 1}}, "Sawai Madhopur": {"section": {"13": 1, "14": 1}}, "Sikar": {"section": {"7": 1, "8": 1, "11": 1, "12": 1, "17": 1}}, "Udaipur": {"section": {"11": 2}}}, "section": {"3": 1, "4": 2, "7": 3, "8": 4, "11": 5, "12": 5, "13": 2, "14": 2, "17": 1, "18": 1}}, "TG": {"districts": {"Mahabubnagar": {"section": {"8": 1}}}, "section": {"8": 1}}, "UP": {"districts": {"Budaun": {"section": {"5": 1, "6": 1}}, "Etah": {"section": {"4": 1}}, "Firozabad": {"section": {"8": 1}}, "Gorakhpur": {"section": {"12": 1}}, "Lucknow": {"section": {"7": 1, "8": 1}}, "Unnao": {"section": {"3": 1, "4": 1}}}, "section": {"3": 1, "4": 2, "5": 1, "6": 1, "7": 1, "8": 2, "12": 1}}, "WB": {"districts": {"Hooghly": {"section": {"4": 1}}, "Paschim Medinpur": {"section": {"6": 1}}}, "section": {"4": 1, "6": 1}}}