{"AP": {"dates": {"2010": {"total": {"total": 4, "pending": 0.0, "disposed": 100.0, "judgement": 0, "pending_agg": 4, "pending_before": 0, "disposed_yearly": 0}}, "2011": {"total": {"total": 12, "pending": 0.0, "disposed": 100.0, "judgement": 0, "pending_agg": 15, "pending_before": 4, "disposed_yearly": 1}}, "2012": {"total": {"total": 12, "pending": 8.333333333333334, "disposed": 91.66666666666667, "judgement": 0, "pending_agg": 26, "pending_before": 15, "disposed_yearly": 1}}, "2013": {"total": {"total": 20, "pending": 0.0, "disposed": 100.0, "judgement": 1, "pending_agg": 41, "pending_before": 26, "disposed_yearly": 5}}, "2014": {"total": {"total": 23, "pending": 8.695652173913043, "disposed": 91.30434782608695, "judgement": 3, "pending_agg": 49, "pending_before": 41, "disposed_yearly": 15}}, "2015": {"total": {"total": 10, "pending": 10.0, "disposed": 90.0, "judgement": 3, "pending_agg": 35, "pending_before": 49, "disposed_yearly": 24}}, "2016": {"total": {"total": 5, "pending": 20.0, "disposed": 80.0, "judgement": 0, "pending_agg": 23, "pending_before": 35, "disposed_yearly": 17}}, "2017": {"total": {"total": 10, "pending": 30.0, "disposed": 70.0, "judgement": 2, "pending_agg": 26, "pending_before": 23, "disposed_yearly": 7}}, "2018": {"total": {"total": 8, "pending": 75.0, "disposed": 25.0, "judgement": 0, "pending_agg": 25, "pending_before": 26, "disposed_yearly": 9}}, "2019": {"total": {"total": 10, "pending": 80.0, "disposed": 20.0, "judgement": 0, "pending_agg": 22, "pending_before": 25, "disposed_yearly": 13}}}}, "AS": {"dates": {"2010": {"total": {"total": 8, "pending": 0.0, "disposed": 100.0, "judgement": 0, "pending_agg": 8, "pending_before": 0, "disposed_yearly": 0}}, "2011": {"total": {"total": 7, "pending": 14.285714285714286, "disposed": 85.71428571428571, "judgement": 0, "pending_agg": 15, "pending_before": 8, "disposed_yearly": 0}}, "2012": {"total": {"total": 7, "pending": 0.0, "disposed": 100.0, "judgement": 0, "pending_agg": 20, "pending_before": 15, "disposed_yearly": 2}}, "2013": {"total": {"total": 8, "pending": 62.5, "disposed": 37.5, "judgement": 0, "pending_agg": 26, "pending_before": 20, "disposed_yearly": 2}}, "2014": {"total": {"total": 15, "pending": 6.666666666666667, "disposed": 93.33333333333333, "judgement": 0, "pending_agg": 31, "pending_before": 26, "disposed_yearly": 10}}, "2015": {"total": {"total": 6, "pending": 0.0, "disposed": 100.0, "judgement": 0, "pending_agg": 29, "pending_before": 31, "disposed_yearly": 8}}, "2016": {"total": {"total": 11, "pending": 18.181818181818183, "disposed": 81.81818181818181, "judgement": 1, "pending_agg": 24, "pending_before": 29, "disposed_yearly": 16}}, "2017": {"total": {"total": 14, "pending": 14.285714285714286, "disposed": 85.71428571428571, "judgement": 0, "pending_agg": 29, "pending_before": 24, "disposed_yearly": 9}}, "2018": {"total": {"total": 15, "pending": 40.0, "disposed": 60.0, "judgement": 1, "pending_agg": 30, "pending_before": 29, "disposed_yearly": 14}}, "2019": {"total": {"total": 13, "pending": 38.46153846153846, "disposed": 61.53846153846154, "judgement": 0, "pending_agg": 23, "pending_before": 30, "disposed_yearly": 20}}, "2020": {"total": {"total": 1, "pending": 0.0, "disposed": 100.0, "judgement": 0, "pending_agg": 22, "pending_before": 23, "disposed_yearly": 2}}}}, "DL": {"dates": {"2014": {"total": {"total": 2, "pending": 50.0, "disposed": 50.0, "judgement": 0, "pending_agg": 2, "pending_before": 0, "disposed_yearly": 0}}, "2015": {"total": {"total": 3, "pending": 66.66666666666667, "disposed": 33.333333333333336, "judgement": 0, "pending_agg": 5, "pending_before": 2, "disposed_yearly": 0}}, "2016": {"total": {"total": 3, "pending": 0.0, "disposed": 100.0, "judgement": 0, "pending_agg": 8, "pending_before": 5, "disposed_yearly": 0}}, "2017": {"total": {"total": 4, "pending": 50.0, "disposed": 50.0, "judgement": 0, "pending_agg": 7, "pending_before": 8, "disposed_yearly": 5}}, "2018": {"total": {"total": 8, "pending": 37.5, "disposed": 62.5, "judgement": 0, "pending_agg": 14, "pending_before": 7, "disposed_yearly": 1}}, "2019": {"total": {"total": 11, "pending": 63.63636363636363, "disposed": 36.36363636363637, "judgement": 0, "pending_agg": 16, "pending_before": 14, "disposed_yearly": 9}}}}, "JH": {"dates": {"2012": {"total": {"total": 3, "pending": 33.333333333333336, "disposed": 66.66666666666667, "judgement": 0, "pending_agg": 3, "pending_before": 0, "disposed_yearly": 0}}, "2013": {"total": {"total": 4, "pending": 75.0, "disposed": 25.0, "judgement": 1, "pending_agg": 7, "pending_before": 3, "disposed_yearly": 0}}, "2014": {"total": {"total": 23, "pending": 47.82608695652174, "disposed": 52.17391304347826, "judgement": 0, "pending_agg": 24, "pending_before": 7, "disposed_yearly": 6}}, "2015": {"total": {"total": 32, "pending": 40.625, "disposed": 59.375, "judgement": 1, "pending_agg": 43, "pending_before": 24, "disposed_yearly": 13}}, "2016": {"total": {"total": 36, "pending": 19.444444444444443, "disposed": 80.55555555555556, "judgement": 1, "pending_agg": 59, "pending_before": 43, "disposed_yearly": 20}}, "2017": {"total": {"total": 98, "pending": 30.612244897959183, "disposed": 69.38775510204081, "judgement": 0, "pending_agg": 97, "pending_before": 59, "disposed_yearly": 60}}, "2018": {"total": {"total": 78, "pending": 26.923076923076923, "disposed": 73.07692307692308, "judgement": 0, "pending_agg": 105, "pending_before": 97, "disposed_yearly": 70}}, "2019": {"total": {"total": 52, "pending": 51.92307692307692, "disposed": 48.07692307692308, "judgement": 0, "pending_agg": 118, "pending_before": 105, "disposed_yearly": 39}}, "2020": {"total": {"total": 8, "pending": 62.5, "disposed": 37.5, "judgement": 0, "pending_agg": 118, "pending_before": 118, "disposed_yearly": 8}}}}, "KA": {"dates": {"2015": {"total": {"total": 2, "pending": 50.0, "disposed": 50.0, "judgement": 0, "pending_agg": 2, "pending_before": 0, "disposed_yearly": 0}}, "2016": {"total": {"total": 10, "pending": 10.0, "disposed": 90.0, "judgement": 8, "pending_agg": 6, "pending_before": 2, "disposed_yearly": 6}}, "2017": {"total": {"total": 1, "pending": 100.0, "disposed": 0.0, "judgement": 0, "pending_agg": 4, "pending_before": 6, "disposed_yearly": 3}}, "2018": {"total": {"total": 2, "pending": 50.0, "disposed": 50.0, "judgement": 0, "pending_agg": 4, "pending_before": 4, "disposed_yearly": 2}}}}, "MH": {"dates": {"2010": {"total": {"total": 2, "pending": 50.0, "disposed": 50.0, "judgement": 1, "pending_agg": 2, "pending_before": 0, "disposed_yearly": 0}}, "2011": {"total": {"total": 5, "pending": 40.0, "disposed": 60.0, "judgement": 3, "pending_agg": 7, "pending_before": 2, "disposed_yearly": 0}}, "2012": {"total": {"total": 49, "pending": 26.53061224489796, "disposed": 73.46938775510205, "judgement": 15, "pending_agg": 45, "pending_before": 7, "disposed_yearly": 11}}, "2013": {"total": {"total": 87, "pending": 37.93103448275862, "disposed": 62.06896551724138, "judgement": 33, "pending_agg": 111, "pending_before": 45, "disposed_yearly": 21}}, "2014": {"total": {"total": 141, "pending": 35.46099290780142, "disposed": 64.53900709219859, "judgement": 42, "pending_agg": 220, "pending_before": 111, "disposed_yearly": 32}}, "2015": {"total": {"total": 171, "pending": 41.52046783625731, "disposed": 58.47953216374269, "judgement": 53, "pending_agg": 333, "pending_before": 220, "disposed_yearly": 58}}, "2016": {"total": {"total": 67, "pending": 46.26865671641791, "disposed": 53.73134328358209, "judgement": 13, "pending_agg": 345, "pending_before": 333, "disposed_yearly": 55}}, "2017": {"total": {"total": 69, "pending": 42.028985507246375, "disposed": 57.971014492753625, "judgement": 16, "pending_agg": 345, "pending_before": 345, "disposed_yearly": 69}}, "2018": {"total": {"total": 83, "pending": 57.83132530120482, "disposed": 42.16867469879518, "judgement": 11, "pending_agg": 349, "pending_before": 345, "disposed_yearly": 79}}, "2019": {"total": {"total": 52, "pending": 75.0, "disposed": 25.0, "judgement": 1, "pending_agg": 326, "pending_before": 349, "disposed_yearly": 75}}, "2020": {"total": {"total": 4, "pending": 75.0, "disposed": 25.0, "judgement": 0, "pending_agg": 320, "pending_before": 326, "disposed_yearly": 10}}}}, "RJ": {"dates": {"2011": {"total": {"total": 2, "pending": 0.0, "disposed": 100.0, "judgement": 1, "pending_agg": 2, "pending_before": 0, "disposed_yearly": 0}}, "2012": {"total": {"total": 2, "pending": 0.0, "disposed": 100.0, "judgement": 0, "pending_agg": 4, "pending_before": 2, "disposed_yearly": 0}}, "2013": {"total": {"total": 8, "pending": 37.5, "disposed": 62.5, "judgement": 1, "pending_agg": 12, "pending_before": 4, "disposed_yearly": 0}}, "2014": {"total": {"total": 30, "pending": 46.666666666666664, "disposed": 53.333333333333336, "judgement": 0, "pending_agg": 41, "pending_before": 12, "disposed_yearly": 1}}, "2015": {"total": {"total": 76, "pending": 38.1578947368421, "disposed": 61.8421052631579, "judgement": 0, "pending_agg": 98, "pending_before": 41, "disposed_yearly": 19}}, "2016": {"total": {"total": 31, "pending": 25.806451612903224, "disposed": 74.19354838709677, "judgement": 0, "pending_agg": 109, "pending_before": 98, "disposed_yearly": 20}}, "2017": {"total": {"total": 43, "pending": 27.906976744186046, "disposed": 72.09302325581395, "judgement": 1, "pending_agg": 114, "pending_before": 109, "disposed_yearly": 38}}, "2018": {"total": {"total": 39, "pending": 35.8974358974359, "disposed": 64.1025641025641, "judgement": 1, "pending_agg": 111, "pending_before": 114, "disposed_yearly": 42}}, "2019": {"total": {"total": 32, "pending": 53.125, "disposed": 46.875, "judgement": 0, "pending_agg": 107, "pending_before": 111, "disposed_yearly": 36}}, "2020": {"total": {"total": 4, "pending": 75.0, "disposed": 25.0, "judgement": 0, "pending_agg": 100, "pending_before": 107, "disposed_yearly": 11}}}}, "TG": {"dates": {"2010": {"total": {"total": 1, "pending": 0.0, "disposed": 100.0, "judgement": 0, "pending_agg": 1, "pending_before": 0, "disposed_yearly": 0}}, "2012": {"total": {"total": 4, "pending": 50.0, "disposed": 50.0, "judgement": 1, "pending_agg": 5, "pending_before": 1, "disposed_yearly": 0}}, "2013": {"total": {"total": 9, "pending": 11.11111111111111, "disposed": 88.88888888888889, "judgement": 0, "pending_agg": 14, "pending_before": 5, "disposed_yearly": 0}}, "2014": {"total": {"total": 2, "pending": 0.0, "disposed": 100.0, "judgement": 1, "pending_agg": 13, "pending_before": 14, "disposed_yearly": 3}}, "2015": {"total": {"total": 2, "pending": 100.0, "disposed": 0.0, "judgement": 0, "pending_agg": 13, "pending_before": 13, "disposed_yearly": 2}}, "2016": {"total": {"total": 4, "pending": 50.0, "disposed": 50.0, "judgement": 0, "pending_agg": 16, "pending_before": 13, "disposed_yearly": 1}}, "2017": {"total": {"total": 3, "pending": 0.0, "disposed": 100.0, "judgement": 1, "pending_agg": 14, "pending_before": 16, "disposed_yearly": 5}}, "2018": {"total": {"total": 1, "pending": 100.0, "disposed": 0.0, "judgement": 0, "pending_agg": 12, "pending_before": 14, "disposed_yearly": 3}}, "2019": {"total": {"total": 5, "pending": 100.0, "disposed": 0.0, "judgement": 0, "pending_agg": 13, "pending_before": 12, "disposed_yearly": 4}}}}, "TN": {"dates": {"2013": {"total": {"total": 1, "pending": 100.0, "disposed": 0.0, "judgement": 0, "pending_agg": 1, "pending_before": 0, "disposed_yearly": 0}}, "2014": {"total": {"total": 3, "pending": 0.0, "disposed": 100.0, "judgement": 2, "pending_agg": 4, "pending_before": 1, "disposed_yearly": 0}}, "2016": {"total": {"total": 3, "pending": 33.333333333333336, "disposed": 66.66666666666667, "judgement": 0, "pending_agg": 3, "pending_before": 3, "disposed_yearly": 3}}, "2018": {"total": {"total": 3, "pending": 66.66666666666667, "disposed": 33.333333333333336, "judgement": 0, "pending_agg": 5, "pending_before": 3, "disposed_yearly": 1}}, "2019": {"total": {"total": 1, "pending": 0.0, "disposed": 100.0, "judgement": 1, "pending_agg": 4, "pending_before": 5, "disposed_yearly": 2}}}}, "UP": {"dates": {"2011": {"total": {"total": 1, "pending": 100.0, "disposed": 0.0, "judgement": 0, "pending_agg": 1, "pending_before": 0, "disposed_yearly": 0}}, "2013": {"total": {"total": 1, "pending": 100.0, "disposed": 0.0, "judgement": 0, "pending_agg": 2, "pending_before": 1, "disposed_yearly": 0}}, "2014": {"total": {"total": 12, "pending": 66.66666666666667, "disposed": 33.333333333333336, "judgement": 0, "pending_agg": 12, "pending_before": 2, "disposed_yearly": 2}}, "2015": {"total": {"total": 17, "pending": 52.94117647058823, "disposed": 47.05882352941177, "judgement": 0, "pending_agg": 21, "pending_before": 12, "disposed_yearly": 8}}, "2016": {"total": {"total": 39, "pending": 58.97435897435897, "disposed": 41.02564102564103, "judgement": 2, "pending_agg": 48, "pending_before": 21, "disposed_yearly": 12}}, "2017": {"total": {"total": 42, "pending": 28.571428571428573, "disposed": 71.42857142857143, "judgement": 0, "pending_agg": 62, "pending_before": 48, "disposed_yearly": 28}}, "2018": {"total": {"total": 71, "pending": 36.61971830985915, "disposed": 63.38028169014085, "judgement": 0, "pending_agg": 100, "pending_before": 62, "disposed_yearly": 33}}, "2019": {"total": {"total": 68, "pending": 63.23529411764706, "disposed": 36.76470588235294, "judgement": 1, "pending_agg": 128, "pending_before": 100, "disposed_yearly": 40}}, "2020": {"total": {"total": 16, "pending": 50.0, "disposed": 50.0, "judgement": 1, "pending_agg": 131, "pending_before": 128, "disposed_yearly": 13}}}}, "WB": {"dates": {"2011": {"total": {"total": 2, "pending": 100.0, "disposed": 0.0, "judgement": 0, "pending_agg": 2, "pending_before": 0, "disposed_yearly": 0}}, "2012": {"total": {"total": 10, "pending": 60.0, "disposed": 40.0, "judgement": 1, "pending_agg": 12, "pending_before": 2, "disposed_yearly": 0}}, "2013": {"total": {"total": 6, "pending": 50.0, "disposed": 50.0, "judgement": 3, "pending_agg": 18, "pending_before": 12, "disposed_yearly": 0}}, "2014": {"total": {"total": 19, "pending": 63.1578947368421, "disposed": 36.8421052631579, "judgement": 4, "pending_agg": 36, "pending_before": 18, "disposed_yearly": 1}}, "2015": {"total": {"total": 13, "pending": 30.76923076923077, "disposed": 69.23076923076923, "judgement": 3, "pending_agg": 46, "pending_before": 36, "disposed_yearly": 3}}, "2016": {"total": {"total": 7, "pending": 71.42857142857143, "disposed": 28.571428571428573, "judgement": 0, "pending_agg": 50, "pending_before": 46, "disposed_yearly": 3}}, "2017": {"total": {"total": 6, "pending": 50.0, "disposed": 50.0, "judgement": 0, "pending_agg": 51, "pending_before": 50, "disposed_yearly": 5}}, "2018": {"total": {"total": 10, "pending": 70.0, "disposed": 30.0, "judgement": 1, "pending_agg": 49, "pending_before": 51, "disposed_yearly": 12}}, "2019": {"total": {"total": 9, "pending": 77.77777777777777, "disposed": 22.22222222222222, "judgement": 0, "pending_agg": 49, "pending_before": 49, "disposed_yearly": 9}}, "2020": {"total": {"total": 1, "pending": 100.0, "disposed": 0.0, "judgement": 0, "pending_agg": 50, "pending_before": 49, "disposed_yearly": 0}}}}, "TT": {"dates": {"2010": {"total": {"total": 15, "pending": 6.666666666666667, "disposed": 93.33333333333333, "judgement": 1, "pending_agg": 15, "pending_before": 0, "disposed_yearly": 0}}, "2011": {"total": {"total": 29, "pending": 20.689655172413794, "disposed": 79.3103448275862, "judgement": 4, "pending_agg": 43, "pending_before": 15, "disposed_yearly": 1}}, "2012": {"total": {"total": 87, "pending": 26.436781609195403, "disposed": 73.5632183908046, "judgement": 17, "pending_agg": 116, "pending_before": 43, "disposed_yearly": 14}}, "2013": {"total": {"total": 144, "pending": 34.72222222222222, "disposed": 65.27777777777777, "judgement": 39, "pending_agg": 232, "pending_before": 116, "disposed_yearly": 28}}, "2014": {"total": {"total": 270, "pending": 36.666666666666664, "disposed": 63.333333333333336, "judgement": 52, "pending_agg": 432, "pending_before": 232, "disposed_yearly": 70}}, "2015": {"total": {"total": 332, "pending": 39.75903614457831, "disposed": 60.24096385542169, "judgement": 60, "pending_agg": 628, "pending_before": 432, "disposed_yearly": 136}}, "2016": {"total": {"total": 216, "pending": 37.5, "disposed": 62.5, "judgement": 25, "pending_agg": 691, "pending_before": 628, "disposed_yearly": 153}}, "2017": {"total": {"total": 290, "pending": 32.41379310344828, "disposed": 67.58620689655173, "judgement": 20, "pending_agg": 752, "pending_before": 691, "disposed_yearly": 229}}, "2018": {"total": {"total": 318, "pending": 42.45283018867924, "disposed": 57.54716981132076, "judgement": 14, "pending_agg": 804, "pending_before": 752, "disposed_yearly": 266}}, "2019": {"total": {"total": 253, "pending": 62.45059288537549, "disposed": 37.54940711462451, "judgement": 3, "pending_agg": 810, "pending_before": 804, "disposed_yearly": 247}}, "2020": {"total": {"total": 34, "pending": 58.8235294117647, "disposed": 41.1764705882353, "judgement": 1, "pending_agg": 799, "pending_before": 810, "disposed_yearly": 45}}}}}